{
  "pmid": "37349024",
  "title": "Trastuzumab deruxtecan for breast cancer: do patients experience a\u00a0comprehensive benefit?",
  "abstract": "",
  "authors": [
    "Mosele F",
    "Di Maio M"
  ],
  "journal": "Annals of oncology : official journal of the European Society for Medical Oncology",
  "publication_date": "2023 Jul",
  "doi": "10.1016/j.annonc.2023.05.011",
  "mesh_terms": [
    "Humans",
    "Female",
    "Breast Neoplasms",
    "Trastuzumab",
    "Camptothecin",
    "Immunoconjugates",
    "Erb-b2 Receptor Tyrosine Kinases"
  ],
  "keywords": [],
  "pubmed_url": "https://pubmed.ncbi.nlm.nih.gov/37349024/",
  "search_category": "ADC breast cancer Enhertu Trodelvy"
}