{
  "pmid": "37863916",
  "title": "Neoadjuvant camrelizumab plus nab-paclitaxel and epirubicin in early triple-negative breast cancer: a single-arm phase II trial.",
  "abstract": "Immunotherapy combined with chemotherapy has been demonstrated to be effective in early triple-negative breast cancer (TNBC). In this single-arm, phase II study with Simon's two-stage design, we investigated the efficacy and safety of neoadjuvant camrelizumab plus chemotherapy in patients with early TNBC (NCT04213898). Eligible female patients aged 18 years or older with histologically confirmed treatment-na\u00efve early TNBC were treated with camrelizumab (200\u2009mg, on day 1), nab-paclitaxel (125\u2009mg/m2, on days 1, 8, and 15), and epirubicin (75\u2009mg/m2, on day 1) every three weeks for six cycles. The primary end point was the pathological complete response; secondary endpoints included safety, objective response rate, and long-term survival outcomes of event-free survival, disease-free survival, and distant disease-free survival. A total of 39 patients were enrolled between January 2020 and October 2021. Twenty-five patients achieved a pathological complete response (64.1%, 95%CI: 47.2,\u00a078.8). The objective response rate was 89.7% (95%CI: 74.8, 96.7), including 35 patients with partial responses. Treatment-related adverse events of grade 3 or 4 occurred in 30 (76.9%) patients. In conclusion, the trial meets the prespecified endpoints showing promising efficacy and manageable safety of neoadjuvant camrelizumab plus nab-paclitaxel and epirubicin chemotherapy in female patients with early TNBC. Long-term survival outcomes are still pending.",
  "authors": [
    "Wang Chengzheng",
    "Liu Zhenzhen",
    "Chen Xiuchun",
    "Qiao Jianghua",
    "Lu Zhenduo",
    "Li Lianfang",
    "Sun Xianfu",
    "Zhang Chongjian",
    "Yue Xiayu",
    "Xia Qingxin",
    "Zhang He",
    "Yan Min"
  ],
  "journal": "Nature communications",
  "publication_date": "2023 Oct",
  "doi": "10.1038/s41467-023-42479-w",
  "mesh_terms": [
    "Female",
    "Humans",
    "Albumins",
    "Antineoplastic Combined Chemotherapy Protocols",
    "Breast Neoplasms",
    "Epirubicin",
    "Neoadjuvant Therapy",
    "Paclitaxel",
    "Treatment Outcome",
    "Triple Negative Breast Neoplasms",
    "Adult",
    "Antibodies, Monoclonal, Humanized"
  ],
  "keywords": [],
  "pubmed_url": "https://pubmed.ncbi.nlm.nih.gov/37863916/",
  "search_category": "TNBC clinical trials outcomes"
}