{
  "pmid": "37633306",
  "title": "Overall survival with sacituzumab govitecan in hormone receptor-positive and human epidermal growth factor receptor 2-negative metastatic breast cancer (TROPiCS-02): a randomised, open-label, multicentre, phase 3 trial.",
  "abstract": "BACKGROUND: Sacituzumab govitecan demonstrated significant progression-free survival benefit over chemotherapy in the phase 3 TROPiCS-02 trial in patients with pretreated, endocrine-resistant hormone receptor-positive, human epidermal growth factor receptor 2-negative (HR+ and HER2-) metastatic breast cancer with limited treatment options. Here, we report the protocol-specified final analysis of overall survival and endpoints by trophoblast cell-surface antigen 2 (Trop-2) expression and other variables.\nMETHODS: In this randomised, open-label, multicentre, phase 3 trial, which took place in 91 centres across North America (the USA and Canada) and Europe (Belgium, France, Germany, Italy, the Netherlands, Spain, and the UK), patients were randomly assigned (1:1) to receive sacituzumab govitecan or chemotherapy (eribulin, vinorelbine, capecitabine, or gemcitabine). Patients had confirmed HR+ and HER2- locally recurrent inoperable or metastatic breast cancer and had received at least one previous endocrine therapy, a taxane, and a CDK4/6 inhibitor in any setting and two to four previous chemotherapy regimens for metastatic disease. The primary endpoint was progression-free survival (previously reported and not included in this analysis), and secondary endpoints included overall survival, objective response rate (ORR), and patient-reported outcomes. Overall survival was assessed using stratified log-rank tests and Cox regression. Trop-2 expression was assessed in tumour tissue by immunohistochemistry. In the statistical testing hierarchy, ORR and patient-reported outcomes were tested sequentially if overall survival was significant. This study is registered with ClinicalTrials.gov, NCT03901339.\nFINDINGS: At the data cutoff date of July 1, 2022, 543 of 776 screened patients were randomly assigned between May 30, 2019, and April 5, 2021, with 272 patients in the sacituzumab govitecan group and 271 patients in the chemotherapy group. With a 12\u00b75-month (IQR 6\u00b74-18\u00b78) median follow-up, 390 deaths occurred among 543 patients. Overall survival was significantly improved with sacituzumab govitecan versus chemotherapy (median 14\u00b74 months [95% CI 13\u00b70-15\u00b77] vs 11\u00b72 months [10\u00b71-12\u00b77]; hazard ratio [HR] 0\u00b779, 95% CI 0\u00b765-0\u00b796; p=0\u00b7020); survival benefit was consistent across Trop-2 expression-level subgroups. ORR was significantly improved with sacituzumab govitecan compared with chemotherapy (57 [21%] patients vs 38 [14%]; odds ratio 1\u00b763 [95% CI 1\u00b703-2\u00b756]; p=0\u00b7035), as was time to deterioration of global health status and quality of life (median 4\u00b73 months vs 3\u00b70 months; HR 0\u00b775 [0\u00b761-0\u00b792]; p=0\u00b70059) and fatigue (median 2\u00b72 months vs 1\u00b74 months; HR 0\u00b773 [0\u00b760-0\u00b789]; p=0\u00b70021). The safety profile of sacituzumab govitecan was consistent with previous studies (including the TROPiCS-02 primary analysis and the ASCENT trial). One fatal adverse event (septic shock caused by neutropenic colitis) was determined to be related to sacituzumab govitecan treatment.\nINTERPRETATION: Sacituzumab govitecan demonstrated statistically significant and clinically meaningful benefit over chemotherapy, with a 3\u00b72-month median overall survival improvement and a manageable safety profile. These data support sacituzumab govitecan as a new treatment option for patients with pretreated, endocrine-resistant HR+ and HER2- metastatic breast cancer.\nFUNDING: Gilead Sciences.",
  "authors": [
    "Rugo Hope S",
    "Bardia Aditya",
    "Marm\u00e9 Frederik",
    "Cort\u00e9s Javier",
    "Schmid Peter",
    "Loirat Delphine",
    "Tr\u00e9dan Olivier",
    "Ciruelos Eva",
    "Dalenc Florence",
    "G\u00f3mez Pardo Patricia",
    "Jhaveri Komal L",
    "Delaney Rosemary",
    "Valdez Theresa",
    "Wang Hao",
    "Motwani Monica",
    "Yoon Oh Kyu",
    "Verret Wendy",
    "Tolaney Sara M"
  ],
  "journal": "Lancet (London, England)",
  "publication_date": "2023 Oct",
  "doi": "10.1016/S0140-6736(23)01245-X",
  "mesh_terms": [
    "Humans",
    "Female",
    "Breast Neoplasms",
    "Quality of Life",
    "Antineoplastic Combined Chemotherapy Protocols",
    "Erb-b2 Receptor Tyrosine Kinases",
    "Camptothecin",
    "Immunoconjugates",
    "Antibodies, Monoclonal, Humanized"
  ],
  "keywords": [],
  "pubmed_url": "https://pubmed.ncbi.nlm.nih.gov/37633306/",
  "search_category": "ADC breast cancer Enhertu Trodelvy"
}