{
  "pmid": "35357621",
  "title": "Awareness and knowledge of Colorectal Cancer Screening among Latinos in Omaha, Nebraska.",
  "abstract": "BACKGROUND: Colorectal cancer (CRC) screening rates remain low in Latino communities. We sought to determine the screening awareness and attitudes in Omaha, Nebraska.\nMETHODS: We interviewed 150 Latinos at an urban Federally Qualified Health Center, June-October 2017. Chi-square or Fisher-exact tests and multiple logistic regression models were used for data analysis.\nRESULTS: Participants reported low educational attainment, low income, and limited access to insurance or a primary provider. Less than one-third of participants aged 50\u2009+\u2009had ever heard of FOBT (32.6%) or colonoscopy (30.4%). For individuals 50+, access to a primary care provider (p\u2009=\u2009.03) and knowing the screening initiation age (p\u2009=\u2009.03) were associated with ever having a colonoscopy. Higher knowledge score was a strong predictor of any CRC screening.\nDISCUSSION: Knowledge predicted screening, suggesting interventions should aim to educate this population regarding CRC screening guidelines and options and work with stakeholders to make CRC screening more accessible.",
  "authors": [
    "Gonzales Roger",
    "Ratnapradipa Kendra",
    "De Alba Armando",
    "Chen Ken",
    "Smith Lynette",
    "Kim Jungyoon",
    "Wang Hongmei",
    "Farazi Paraskevi A"
  ],
  "journal": "Journal of immigrant and minority health",
  "publication_date": "2023 Feb",
  "doi": "10.1007/s10903-022-01358-0",
  "mesh_terms": [
    "Humans",
    "Nebraska",
    "Early Detection of Cancer",
    "Health Knowledge, Attitudes, Practice",
    "Colorectal Neoplasms",
    "Hispanic or Latino",
    "Colonoscopy",
    "Mass Screening"
  ],
  "keywords": [
    "Awareness",
    "Colorectal cancer screening",
    "Health disparity",
    "Latinos"
  ],
  "pubmed_url": "https://pubmed.ncbi.nlm.nih.gov/35357621/",
  "search_category": "Colorectal cancer screening disparities"
}