{
  "nct_id": "NCT00256880",
  "brief_title": "Pazopanib (GW786034) In Subjects With Relapsed Or Refractory Multiple Myeloma",
  "official_title": "A Phase II, Open-Label Study of Pazopanib (GW786034) in Patients With Relapsed or Refractory Multiple Myeloma",
  "brief_summary": "The purpose of this study is to determine how effective and safe a new investigational drug is in treating patients with relapsed or refractory multiple myeloma. The treatment involves daily dosing. A patient may continue to receive the treatment as long as they are benefiting from the treatment. Blood samples will be taken at specific times to measure the amount of drug in your body at specific times after the drug is given. Blood samples will also be taken for lab tests such as complete blood counts and clinical chemistries. Physical exams will be performed before each treatment. During the treatment phase, the patients will undergo regular assessments for safety and clinical response.",
  "detailed_description": "",
  "overall_status": "COMPLETED",
  "phase": [
    "PHASE2"
  ],
  "study_type": "INTERVENTIONAL",
  "enrollment": 100,
  "conditions": [
    "Carcinoma, Renal Cell"
  ],
  "interventions": [
    {
      "name": "GW786034",
      "type": "DRUG",
      "description": ""
    }
  ],
  "eligibility": {
    "criteria": "Inclusion criteria:\n\n* Must have diagnosis of relapsed or refractory multiple.\n* bone marrow function \\[ANC (absolute neutrophil count) greater than 1000/mm3\\]; platelet count greater than or equal to 75,000/mm3.\n* renal function (calculated creatinine clearance \\>50 mL.min, albumin less than or equal to 500 mg).\n\nExclusion criteria:\n\n* Failed more than 3 prior lines of therapy including stem cell transplant.\n* Females who are pregnant or nursing.\n* Unstable blood pressure.\n* Significant heart conditions or history of thrombosis.\n* Any unstable, pre-existing major medical condition or history of other cancers.\n* Have received an investigational drug, chemotherapy, radiation treatment or surgery within 28 days prior to entering the study.",
    "gender": "ALL",
    "min_age": "21 Years",
    "max_age": "",
    "healthy_volunteers": false
  },
  "locations": [
    {
      "facility": "GSK Investigational Site",
      "city": "Philadelphia",
      "state": "Pennsylvania",
      "zip": "19104",
      "status": ""
    }
  ],
  "primary_outcomes": [
    {
      "measure": "Evaluate the safety and tolerability of GW786034 in patients with relapsed or refractory multiple myeloma (MM).",
      "timeFrame": "",
      "description": ""
    }
  ],
  "sponsor": "GlaxoSmithKline",
  "collaborators": [],
  "start_date": "2005-01",
  "completion_date": "2005-12",
  "last_updated": "2017-01-16"
}